GenerateFiles/__init__.py
GenerateFiles/generate_files.py
GenerateFiles/save_file.py
generate_files-1.0.1.dist-info/LICENSE.txt
generate_files-1.0.1.dist-info/METADATA
generate_files-1.0.1.dist-info/WHEEL
generate_files-1.0.1.dist-info/top_level.txt
generate_files-1.0.1.dist-info/RECORD
